<?xml version="1.0" encoding="UTF-8" standalone="yes"?>
<data-set xmlns:xsi="http://www.w3.org/2001/XMLSchema-instance">
	<SPRITE>
		<Name>0</Name>
		<Count>0</Count>
		<Clip0>0</Clip0>
		<Clip1>0</Clip1>
		<Clip2>0</Clip2>
		<Clip3>0</Clip3>
		<Clip4>0</Clip4>
		<Clip5>0</Clip5>
		<Clip6>0</Clip6>
		<Clip7>0</Clip7>
		<Clip8>0</Clip8>
		<Clip9>0</Clip9>
	</SPRITE>
	<SPRITE>
		<Name>0</Name>
		<Count>0</Count>
		<Clip0>0</Clip0>
		<Clip1>0</Clip1>
		<Clip2>0</Clip2>
		<Clip3>0</Clip3>
		<Clip4>0</Clip4>
		<Clip5>0</Clip5>
		<Clip6>0</Clip6>
		<Clip7>0</Clip7>
		<Clip8>0</Clip8>
		<Clip9>0</Clip9>
	</SPRITE>
</data-set>